wirepas_dlms_tool/__about__.py
wirepas_dlms_tool/__init__.py
wirepas_dlms_tool/association_level_enum.py
wirepas_dlms_tool/client.py
wirepas_dlms_tool/dlms_network_interface.py
wirepas_dlms_tool/error_code_enum.py
wirepas_dlms_tool/meter.py
wirepas_dlms_tool/parsed_data.py
wirepas_dlms_tool/profile_generic.py
wirepas_dlms_tool/response.py
wirepas_dlms_tool-1.0rc1.dist-info/LICENSE
wirepas_dlms_tool-1.0rc1.dist-info/METADATA
wirepas_dlms_tool-1.0rc1.dist-info/WHEEL
wirepas_dlms_tool-1.0rc1.dist-info/top_level.txt
wirepas_dlms_tool-1.0rc1.dist-info/RECORD
