Metadata-Version: 2.1
Name: wirepas-dlms-tool
Version: 1.0rc1
Summary: Tool to validate the integration of Wirepas dlms app
Author: Wirepas Ltd
Author-email: opensource@wirepas.com
License: Apache-2
Keywords: Wirepas DLMS HES testing meters
Classifier: Development Status :: 5 - Production/Stable
Classifier: Intended Audience :: Developers
Classifier: License :: OSI Approved :: Apache Software License
Classifier: Topic :: Software Development :: Libraries
Classifier: Programming Language :: Python :: 3
License-File: LICENSE
Requires-Dist: gurux-dlms ==1.0.143
Requires-Dist: wirepas-mqtt-library ==1.2.3
